nz_house_prices/__init__.py
nz_house_prices/api.py
nz_house_prices/cli.py
nz_house_prices/py.typed
nz_house_prices/config/__init__.py
nz_house_prices/config/loader.py
nz_house_prices/core/__init__.py
nz_house_prices/core/driver.py
nz_house_prices/core/parallel.py
nz_house_prices/core/scraper.py
nz_house_prices/core/selectors.py
nz_house_prices/discovery/__init__.py
nz_house_prices/discovery/address.py
nz_house_prices/discovery/cache.py
nz_house_prices/discovery/geocoder.py
nz_house_prices/discovery/resolver.py
nz_house_prices/models/__init__.py
nz_house_prices/models/results.py
nz_house_prices/sites/__init__.py
nz_house_prices/sites/base.py
nz_house_prices/sites/homes.py
nz_house_prices/sites/oneroof.py
nz_house_prices/sites/propertyvalue.py
nz_house_prices/sites/qv.py
nz_house_prices/sites/realestate.py
nz_house_prices/utils/__init__.py
nz_house_prices/utils/logging.py
nz_house_prices/utils/price_format.py
nz_house_prices/utils/rate_limit.py
nz_house_prices/utils/retry.py
nz_house_prices-2.0.1.dist-info/licenses/LICENSE
nz_house_prices-2.0.1.dist-info/METADATA
nz_house_prices-2.0.1.dist-info/WHEEL
nz_house_prices-2.0.1.dist-info/entry_points.txt
nz_house_prices-2.0.1.dist-info/top_level.txt
nz_house_prices-2.0.1.dist-info/RECORD
