Metadata-Version: 2.4
Name: nz-house-prices
Version: 2.0.1
Summary: Scrape house price estimates from NZ real estate websites
Author: Gio
License-Expression: MIT
Keywords: house prices,real estate,new zealand,scraping,property
Classifier: Development Status :: 4 - Beta
Classifier: Intended Audience :: Developers
Classifier: Programming Language :: Python :: 3
Classifier: Programming Language :: Python :: 3.9
Classifier: Programming Language :: Python :: 3.10
Classifier: Programming Language :: Python :: 3.11
Classifier: Programming Language :: Python :: 3.12
Classifier: Programming Language :: Python :: 3.13
Classifier: Topic :: Internet :: WWW/HTTP :: Indexing/Search
Classifier: Topic :: Office/Business :: Financial :: Investment
Requires-Python: >=3.9
License-File: LICENSE
Requires-Dist: playwright>=1.40.0
Requires-Dist: PyYAML>=6.0
Requires-Dist: numpy>=1.26.0
Requires-Dist: requests>=2.28.0
Requires-Dist: rapidfuzz>=3.0.0
Provides-Extra: sheets
Requires-Dist: gspread>=6.1.0; extra == "sheets"
Requires-Dist: oauth2client>=4.1.3; extra == "sheets"
Provides-Extra: dev
Requires-Dist: pytest>=7.0; extra == "dev"
Requires-Dist: pytest-cov; extra == "dev"
Requires-Dist: ruff; extra == "dev"
Requires-Dist: mypy; extra == "dev"
Dynamic: license-file
